RPanY.v
// Yuan Miguel A. Panlilio S07

// Module Name : RPanY
// F(A,B,C,D) = πM(0,1,5,8,9,13)
// Simplificqtion using K-Maps: 
// 1. (B+C+D)(C+D')
// 2. C+((B+D)(D'))
// 3. C + BD'

module RPanY(A, B, C, D, F);
    input A, B, C, D;
    output reg F;

    always @(B,C,D)
    begin
        F = B&~D | C;
    end
endmodule

RPanY_tb.v
// Yuan Miguel A. Panlilio S07

`timescale 1ns / 1ps

module RPanY_tb();
    reg[3:0] t_input;
    wire t_F;
    integer i;

    RPanY dut(t_input[3], t_input[2], t_input[1], t_input[0],t_F);

    initial 
    begin
        t_input = 4'b0000;
        for (i =1; i < 17; i = i+1)
            begin
                #10 t_input = i;
            end
    end

    initial
    begin
        $display("Yuan Miguel A. Panlilio");
        $display("F(A,B,C,D) = πM(0,1,5,8,9,13)");
        $display("Behavioral");
        
        $monitor("time = %0d",$time, " A = %b B = %b C = %b D = %b output_F = %b", t_input[3], t_input[2], t_input[1], t_input[0], t_F);
        $dumpfile("RPanY.vcd");
        $dumpvars();
    end
endmodule

RPanY.vcd
$date
	Sun Mar 08 20:07:08 2026
$end
$version
	Icarus Verilog
$end
$timescale
	1ps
$end
$scope module RPanY_tb $end
$var wire 1 ! t_F $end
$var reg 4 " t_input [3:0] $end
$var integer 32 # i [31:0] $end
$scope module dut $end
$var wire 1 $ A $end
$var wire 1 % B $end
$var wire 1 & C $end
$var wire 1 ' D $end
$var reg 1 ! F $end
$upscope $end
$upscope $end
$enddefinitions $end
$comment Show the parameter values. $end
$dumpall
$end
#0
$dumpvars
0'
0&
0%
0$
b1 #
b0 "
0!
$end
#10000
1'
b10 #
b1 "
#20000
1!
1&
0'
b11 #
b10 "
#30000
1'
b100 #
b11 "
#40000
1%
0&
0'
b101 #
b100 "
#50000
0!
1'
b110 #
b101 "
#60000
1!
1&
0'
b111 #
b110 "
#70000
1'
b1000 #
b111 "
#80000
0!
1$
0%
0&
0'
b1001 #
b1000 "
#90000
1'
b1010 #
b1001 "
#100000
1!
1&
0'
b1011 #
b1010 "
#110000
1'
b1100 #
b1011 "
#120000
1%
0&
0'
b1101 #
b1100 "
#130000
0!
1'
b1110 #
b1101 "
#140000
1!
1&
0'
b1111 #
b1110 "
#150000
1'
b10000 #
b1111 "
#160000
0!
0$
0%
0&
0'
b10001 #
b0 "
